<?xml version="1.0" encoding="utf-8" ?>
<dwsync>
<file name="SourceSansPro-BlackItalic.ttf" server="ftp.carlomainardi.it/www.carlomainardi.it/p5/" local="129881592000000000" remote="132010805400000000" Dst="2" />
<file name="SourceSansPro-Black.ttf" server="ftp.carlomainardi.it/www.carlomainardi.it/p5/" local="129881592000000000" remote="132010805400000000" Dst="2" />
<file name="SourceSansPro-BoldItalic.ttf" server="ftp.carlomainardi.it/www.carlomainardi.it/p5/" local="129881592000000000" remote="132010805400000000" Dst="2" />
<file name="SourceSansPro-Bold.ttf" server="ftp.carlomainardi.it/www.carlomainardi.it/p5/" local="129881592000000000" remote="132010805400000000" Dst="2" />
<file name="SourceSansPro-ExtraLight.ttf" server="ftp.carlomainardi.it/www.carlomainardi.it/p5/" local="129881592000000000" remote="132010805400000000" Dst="2" />
<file name="SourceSansPro-ExtraLightItalic.ttf" server="ftp.carlomainardi.it/www.carlomainardi.it/p5/" local="129881592000000000" remote="132010805400000000" Dst="2" />
<file name="SourceSansPro-Italic.ttf" server="ftp.carlomainardi.it/www.carlomainardi.it/p5/" local="129881592000000000" remote="132010805400000000" Dst="2" />
<file name="SourceSansPro-Light.ttf" server="ftp.carlomainardi.it/www.carlomainardi.it/p5/" local="129881592000000000" remote="132010805400000000" Dst="2" />
<file name="SourceSansPro-LightItalic.ttf" server="ftp.carlomainardi.it/www.carlomainardi.it/p5/" local="129881592000000000" remote="132010805400000000" Dst="2" />
<file name="SourceSansPro-Regular.ttf" server="ftp.carlomainardi.it/www.carlomainardi.it/p5/" local="129881592000000000" remote="132010805400000000" Dst="2" />
<file name="SourceSansPro-SemiBold.ttf" server="ftp.carlomainardi.it/www.carlomainardi.it/p5/" local="129881592000000000" remote="132010805400000000" Dst="2" />
<file name="SourceSansPro-SemiBoldItalic.ttf" server="ftp.carlomainardi.it/www.carlomainardi.it/p5/" local="129881592000000000" remote="132010805400000000" Dst="2" />
</dwsync>